pyrate4site.cpython-311-darwin.so
pyrate4site-0.1.0.dist-info/METADATA
pyrate4site-0.1.0.dist-info/WHEEL
pyrate4site-0.1.0.dist-info/top_level.txt
pyrate4site-0.1.0.dist-info/RECORD
