Metadata-Version: 2.4
Name: pyrate4site
Version: 0.1.0
Summary: Python implementation of Rate4Site
Author: Pegerto Fernandez
Author-email: pegerto@gmail.com
Requires-Python: >=3.7
Provides-Extra: test
Requires-Dist: pytest>=6.0; extra == "test"
Dynamic: author
Dynamic: author-email
Dynamic: provides-extra
Dynamic: requires-python
Dynamic: summary
